file_splitter_harsh/__init__.py
file_splitter_harsh/splitter.py
tests/__init__.py
tests/test_splitter.py
file_splitter_harsh-1.0.6.dist-info/LICENSE
file_splitter_harsh-1.0.6.dist-info/METADATA
file_splitter_harsh-1.0.6.dist-info/WHEEL
file_splitter_harsh-1.0.6.dist-info/top_level.txt
file_splitter_harsh-1.0.6.dist-info/RECORD
