Metadata-Version: 2.2
Name: file_splitter_harsh
Version: 1.0.6
Summary: A simple Python library to split large text files into smaller parts.
Home-page: https://github.com/harshh351998/filesplitter.git
Download-URL: https://github.com/harshh351998/filesplitter/archive/refs/tags/1.0.0.tar.gz
Author: Harsh Mendapara
Author-email: mendapara.harsh47@gmail.com
Classifier: Programming Language :: Python :: 3
Classifier: License :: OSI Approved :: MIT License
Classifier: Operating System :: OS Independent
Requires-Python: >=3.6
License-File: LICENSE
Dynamic: author
Dynamic: author-email
Dynamic: classifier
Dynamic: description
Dynamic: description-content-type
Dynamic: download-url
Dynamic: home-page
Dynamic: requires-python
Dynamic: summary
